{
    "Users":[
        {
            "id":1,
            "firstName":"Nithin",
            "lastName":"Samuel",
            "email":"ns@gmail.com",
            "mobile":"9874563210",
            "salary":"150000"
        },
        {
            "id":2,
            "firstName":"Rian",
            "lastName":"Samuel",
            "email":"res@gmail.com",
            "mobile":"789456320",
            "salary":"3215456"
        },
        {
            "id":3,
            "firstName":"Jeeva",
            "lastName":"Winpray",
            "email":"jw@gmail.com",
            "mobile":"852147963",
            "salary":"550000"
        },
        {
            "id":4,
            "firstName":"Navin",
            "lastName":"Samuel",
            "email":"ns@gmail.com",
            "mobile":"321456987",
            "salary":"160000"
        },
        {
            "id":5,
            "firstName":"Frank",
            "lastName":"Lampard",
            "email":"fl@gmail.com",
            "mobile":"45688888",
            "salary":"250000"
        },
        {
            "id":6,
            "firstName":"Didier",
            "lastName":"Drogba",
            "email":"dd@gmail.com",
            "mobile":"33666444",
            "salary":"120000"
        },
        {
            "id":7,
            "firstName":"Cristiano",
            "lastName":"Ronaldo",
            "email":"cr@gmail.com",
            "mobile":"0123654789",
            "salary":"250000"
        },
        {
            "id":8,
            "firstName":"Lionel",
            "lastName":"Messi",
            "email":"lm@gmail.com",
            "mobile":"123654789",
            "salary":"350000"
        },
        {
            "id":9,
            "firstName":"Neymar",
            "lastName":"Jr",
            "email":"njr@gmail.com",
            "mobile":"1111111",
            "salary":"450000"
        },
        {
            "id":10,
            "firstName":"Luka",
            "lastName":"Modric",
            "email":"lm@gmail.com",
            "mobile":"0850214793",
            "salary":"550000"
        },
        {
            "id":11,
            "firstName":"Kylian",
            "lastName":"Mbappe",
            "email":"km@gmail.com",
            "mobile":"879654123",
            "salary":"650000"
        },
        {
            "id":12,
            "firstName":"John",
            "lastName":"Terry",
            "email":"jt@gmail.com",
            "mobile":"963258741",
            "salary":"750000"
        }
    ]
}